quis/__init__.py
quis/quis.json
quis/quis.py
quis-0.2.0.dist-info/LICENSE
quis-0.2.0.dist-info/METADATA
quis-0.2.0.dist-info/WHEEL
quis-0.2.0.dist-info/RECORD
