Metadata-Version: 2.1
Name: quis
Version: 0.2.0
Summary: A Quantum Instruction Set
License: Apache-2.0
Keywords: quantum,instructions,computation
Author: Quantum Inspire
Author-email: support@quantum-inspire.com
Requires-Python: >=3.9,<4.0
Classifier: Development Status :: 3 - Alpha
Classifier: License :: OSI Approved :: Apache Software License
Classifier: Programming Language :: Python :: 3
Classifier: Programming Language :: Python :: 3.9
Classifier: Programming Language :: Python :: 3.10
Classifier: Programming Language :: Python :: 3.11
Classifier: Programming Language :: Python :: 3.12
